midas/__init__.py
tests/__init__.py
tests/test_api.py
midastest-0.0.1.dist-info/LICENSE
midastest-0.0.1.dist-info/METADATA
midastest-0.0.1.dist-info/WHEEL
midastest-0.0.1.dist-info/top_level.txt
midastest-0.0.1.dist-info/RECORD
