Metadata-Version: 2.1
Name: midastest
Version: 0.0.1
Summary: Gold testing toolkit
Home-page: https://github.com/sonoflilit/midas
Author: Aur Saraf
Author-email: sonoflilit@gmail.com
License: UNKNOWN
Project-URL: Bug Tracker, https://github.com/SonOfLilit/midas/issues
Keywords: gold snapshot test testing regression
Platform: UNKNOWN
Classifier: Development Status :: 3 - Alpha
Classifier: Environment :: Console
Classifier: Framework :: Pytest
Classifier: Topic :: Software Development :: Testing
Classifier: Topic :: Software Development :: Libraries
Classifier: Topic :: Utilities
Classifier: Programming Language :: Python :: 3
Classifier: License :: OSI Approved :: MIT License
Classifier: Operating System :: OS Independent
Requires-Python: >=3.6
License-File: LICENSE
Requires-Dist: pytest
